aws_ad/ADFSAuth.py
aws_ad/__init__.py
aws_ad-0.6.5.dist-info/METADATA
aws_ad-0.6.5.dist-info/RECORD
aws_ad-0.6.5.dist-info/WHEEL
aws_ad-0.6.5.dist-info/entry_points.txt
aws_ad-0.6.5.dist-info/top_level.txt
