Metadata-Version: 2.1
Name: aws-ad
Version: 0.6.5
Summary: A tool for logging into aws with ad credentials
Home-page: https://github.com/ReverseEsper/aws-windows
Author: Adam Kurowski
Author-email: adam.kurowski.git@darevee.pl
License: UNKNOWN
Platform: UNKNOWN
Classifier: Programming Language :: Python :: 3
Classifier: License :: OSI Approved :: MIT License
Classifier: Operating System :: OS Independent
Requires-Dist: bs4
Requires-Dist: boto3
Requires-Dist: configparser
Requires-Dist: argparse
Requires-Dist: requests
Requires-Dist: ConfigArgParse
